sqlite_index/__init__.py
sqlite_index/sqlite_index.py
sqlite_index-1.0.1.dist-info/METADATA
sqlite_index-1.0.1.dist-info/WHEEL
sqlite_index-1.0.1.dist-info/top_level.txt
sqlite_index-1.0.1.dist-info/RECORD
