Metadata-Version: 2.1
Name: sqlite-index
Version: 1.0.1
Summary: Indexes and searches data in a simple sqlite database
Home-page: UNKNOWN
Author: Kenneth Gabriel
Author-email: kennethgabriel78@gmail.com
License: UNKNOWN
Keywords: python,json,index,sqlite,search,python3
Platform: UNKNOWN
Classifier: Development Status :: 1 - Planning
Classifier: Intended Audience :: Developers
Classifier: Programming Language :: Python :: 3
Classifier: Operating System :: Unix
Classifier: Operating System :: MacOS :: MacOS X
Classifier: Operating System :: Microsoft :: Windows
